setup.cfg
setup.py
mdx_picture/__init__.py
mdx_picture/picture.py
mdx_picture.egg-info/PKG-INFO
mdx_picture.egg-info/SOURCES.txt
mdx_picture.egg-info/dependency_links.txt
mdx_picture.egg-info/requires.txt
mdx_picture.egg-info/top_level.txt
mdx_picture/tests/__init__.py
mdx_picture/tests/__main__.py
mdx_picture/tests/test_block_elem_order.py
mdx_picture/tests/test_valid_block.py