Metadata-Version: 1.1
Name: mdx-picture
Version: 0.1.2
Summary: Python-Markdown extension supports the <picture> tag.
Home-page: https://github.com/speechkey/mdx_picture
Author: Artem Grebenkin
Author-email: speechkey@gmail.com
License: MIT License
Download-URL: https://github.com/speechkey/mdx_picture/tarball/0.1.2
Keywords: markdown,picture
Platform: any
Classifier: Development Status :: 4 - Beta
Classifier: License :: OSI Approved :: BSD License
Classifier: Intended Audience :: Developers
Classifier: Environment :: Web Environment
Classifier: Programming Language :: Python
Classifier: Topic :: Text Processing :: Filters
Classifier: Topic :: Text Processing :: Markup :: HTML
